.gitlab-ci.yml
LICENSE.rst
MANIFEST.in
README.md
doc-requirements.txt
pylint-requirements.txt
pylintrc
pypi-intro.rst
pytest.ini
setup.cfg
setup.py
tox.ini
versioneer.py
docs/Configuring.rst
docs/GettingStarted.rst
docs/Makefile
docs/Reference.rst
docs/conf.py
docs/index.rst
docs/_static/.empty
docs/_templates/.empty
src/eso_downloader/__init__.py
src/eso_downloader/__main__.py
src/eso_downloader/_version.py
src/eso_downloader/auth.py
src/eso_downloader/cli.py
src/eso_downloader/datalink.py
src/eso_downloader/night_log.py
src/eso_downloader/pooled_writer.py
src/eso_downloader/program_request.py
src/eso_downloader/tap.py
src/eso_downloader/utils.py
src/eso_downloader/writer.py
src/eso_downloader.egg-info/PKG-INFO
src/eso_downloader.egg-info/SOURCES.txt
src/eso_downloader.egg-info/dependency_links.txt
src/eso_downloader.egg-info/entry_points.txt
src/eso_downloader.egg-info/requires.txt
src/eso_downloader.egg-info/top_level.txt
tests/test_auth.py
tests/test_cli.py
tests/test_datalink.py
tests/test_night_log.py
tests/test_pooled_writer.py
tests/test_program_request.py
tests/test_tap.py
tests/test_utils.py
tests/test_writer.py
tests/data/datalink_results/modern_muse_datalink.vot
tests/data/datalink_results/old_datalink.vot
tests/data/datalink_results/uves_calib_datalink.vot
tests/data/nightlogs/SPHER.2016-09-26T03 04 09.308.NL.txt