Metadata-Version: 2.1
Name: eso-downloader
Version: 0.1
Summary: Downloader for public and proprietary ESO archive data
Home-page: https://eso_downloader.readthedocs.io
Author: James Tocknell
Author-email: james.tocknell@mq.edu.au
License: 3-clause BSD
Project-URL: Documentation, https://eso-downloader.readthedocs.io
Project-URL: Source, https://dev.aao.org.au/adacs/eso-downloader/
Project-URL: Tracker, https://dev.aao.org.au/adacs/eso-downloader/issues
Keywords: ESO archive download astronomy astropy
Classifier: Development Status :: 3 - Alpha
Classifier: Intended Audience :: Developers
Classifier: Intended Audience :: Science/Research
Classifier: License :: OSI Approved :: BSD License
Classifier: Topic :: Scientific/Engineering
Classifier: Programming Language :: Python :: 3
Classifier: Programming Language :: Python :: 3.7
Classifier: Programming Language :: Python :: 3.8
Classifier: Programming Language :: Python :: 3.9
Classifier: Programming Language :: Python :: 3.10
Classifier: Programming Language :: Python :: 3.11
Classifier: Programming Language :: Python :: 3 :: Only
Requires-Python: >=3.7
License-File: LICENSE.rst
